ai_assistant/__init__.py
ai_assistant/consts.py
ai_assistant/interfaces.py
ai_assistant/llm_cli.py
ai_assistant/prompt_llm.py
auto_code/__init__.py
auto_code/cli.py
auto_code/error_handling.py
file_processing/__init__.py
file_processing/error_handling.py
file_processing/file.py
file_processing/file_handling.py
file_processing/llm_file.py
ano_code-8.0.34.dist-info/METADATA
ano_code-8.0.34.dist-info/WHEEL
ano_code-8.0.34.dist-info/entry_points.txt
ano_code-8.0.34.dist-info/top_level.txt
ano_code-8.0.34.dist-info/RECORD
