Metadata-Version: 2.4
Name: ano-code
Version: 8.0.34
Classifier: Programming Language :: Python :: 3
Classifier: License :: OSI Approved :: MIT License
Classifier: Operating System :: OS Independent
Requires-Dist: yaspin==3.1.0
Requires-Dist: click==8.1.7
Requires-Dist: groq==0.11.0
Requires-Dist: openai==1.52.2
Requires-Dist: transformers==4.48.1
Requires-Dist: pathspec==0.12.1
Dynamic: classifier
Dynamic: requires-dist
